{
	"pattrstorage" : 	{
		"name" : "Vsynth",
		"slots" : 		{
			"1" : 			{
				"id" : 1,
				"data" : 				{
					"vs_displacement::displacement_gui::displacement_scale_xm" : [ 0.0 ],
					"vs_displacement::displacement_gui::displacement_anglemenu" : [ 3.0 ],
					"vs_displacement::displacement_gui::displacement_y_range" : [ 2.0 ],
					"vs_displacement::displacement_gui::displacement_angle_range" : [ 0.0 ],
					"vs_displacement::displacement_gui::displacement_scale_ym" : [ 0.0 ],
					"vs_displacement::displacement_gui::displacement_x_range" : [ 2.0 ],
					"vs_displacement::displacement_gui::displacement_angle" : [ 0.0 ],
					"vs_displacement::displacement_gui::displacement_angle_m" : [ 0.017322834645669 ],
					"vs_displacement::displacement_gui::displacement_x" : [ 0.0 ],
					"vs_displacement::displacement_gui::displacement_x_m" : [ 0.01 ],
					"vs_displacement::displacement_gui::displacement_y" : [ 0.0 ],
					"vs_displacement::displacement_gui::displacement_y_m" : [ -0.01 ],
					"vs_displacement::displacement_gui::displacement_zoom" : [ 1.0 ],
					"vs_displacement::displacement_gui::displacement_zoom_m" : [ 0.003149606299213 ],
					"vs_displacement::displacement_boundmode" : [ 2.0 ],
					"vs_displacement::displacement_init_point" : [ 1.0 ],
					"vs_displacement::displacement_polar" : [ 1.0 ],
					"vs_luma_key::luma_invert" : [ 0.0 ],
					"vs_luma_key::luma_smth" : [ 0.448818897637796 ],
					"vs_luma_key::luma_thrshld" : [ 0.181101543307087 ],
					"vs_displacement[1]::displacement_gui::displacement_y_range" : [ 2.0 ],
					"vs_displacement[1]::displacement_gui::displacement_x_range" : [ 2.0 ],
					"vs_displacement[1]::displacement_gui::displacement_scale_xm" : [ 2.0 ],
					"vs_displacement[1]::displacement_gui::displacement_angle_range" : [ 2.0 ],
					"vs_displacement[1]::displacement_gui::displacement_scale_ym" : [ 2.0 ],
					"vs_displacement[1]::displacement_gui::displacement_anglemenu" : [ 3.0 ],
					"vs_displacement[1]::displacement_gui::displacement_angle" : [ 180.0 ],
					"vs_displacement[1]::displacement_gui::displacement_angle_m" : [ 0.0 ],
					"vs_displacement[1]::displacement_gui::displacement_x" : [ 0.0 ],
					"vs_displacement[1]::displacement_gui::displacement_x_m" : [ 0.0 ],
					"vs_displacement[1]::displacement_gui::displacement_y" : [ 0.0 ],
					"vs_displacement[1]::displacement_gui::displacement_y_m" : [ 0.0 ],
					"vs_displacement[1]::displacement_gui::displacement_zoom" : [ 0.954566929133859 ],
					"vs_displacement[1]::displacement_gui::displacement_zoom_m" : [ 0.006299212598425 ],
					"vs_displacement[1]::displacement_boundmode" : [ 1.0 ],
					"vs_displacement[1]::displacement_init_point" : [ 1.0 ],
					"vs_displacement[1]::displacement_polar" : [ 0.0 ],
					"vs_wfg_3::wfg3_pm_range" : [ 0.0 ],
					"vs_wfg_3::wfg3_freq_range" : [ 0.0 ],
					"vs_wfg_3::wfg3_fm_range" : [ 0.0 ],
					"vs_wfg_3::wfg3_angle" : [ 45.764705882352942 ],
					"vs_wfg_3::wfg3_bias" : [ 41.73228346456694 ],
					"vs_wfg_3::wfg3_biasm" : [ 0.37007874015748 ],
					"vs_wfg_3::wfg3_fm" : [ 0.535433070866142 ],
					"vs_wfg_3::wfg3_freq" : [ 38.092425990003839 ],
					"vs_wfg_3::wfg3_pm" : [ 0.905511811023622 ],
					"vs_wfg_3::wfg3_shape" : [ 1.0 ],
					"vs_wfg_3::wfg3_speed" : [ 0.352549019607843 ],
					"vs_wfg_3[1]::wfg3_freq_range" : [ 0.0 ],
					"vs_wfg_3[1]::wfg3_pm_range" : [ 0.0 ],
					"vs_wfg_3[1]::wfg3_fm_range" : [ 0.0 ],
					"vs_wfg_3[1]::wfg3_angle" : [ 0.0 ],
					"vs_wfg_3[1]::wfg3_bias" : [ 50.0 ],
					"vs_wfg_3[1]::wfg3_biasm" : [ 0.0 ],
					"vs_wfg_3[1]::wfg3_fm" : [ 0.0 ],
					"vs_wfg_3[1]::wfg3_freq" : [ 60.0 ],
					"vs_wfg_3[1]::wfg3_pm" : [ 0.0 ],
					"vs_wfg_3[1]::wfg3_shape" : [ 0.75 ],
					"vs_wfg_3[1]::wfg3_speed" : [ 0.1 ],
					"vs_filter_temp::temp_freq" : [ 0.78740157480315 ],
					"vs_lfo::lfo_freq_range" : [ 1.0 ],
					"vs_lfo::lfo_freq" : [ 0.1 ],
					"vs_lfo::lfo_pw" : [ 50.0 ],
					"vs_lfo::lfo_wave" : [ 0.0 ],
					"vs_lfo::umenu" : [ 0 ],
					"vs_lfo[1]::lfo_freq_range" : [ 1.0 ],
					"vs_lfo[1]::lfo_freq" : [ 0.1 ],
					"vs_lfo[1]::lfo_pw" : [ 50.0 ],
					"vs_lfo[1]::lfo_wave" : [ 0.0 ],
					"vs_lfo[1]::umenu" : [ 0 ],
					"vs_lfo[2]::lfo_freq_range" : [ 1.0 ],
					"vs_lfo[2]::lfo_freq" : [ 0.2 ],
					"vs_lfo[2]::lfo_pw" : [ 50.0 ],
					"vs_lfo[2]::lfo_wave" : [ 0.0 ],
					"vs_lfo[2]::umenu" : [ 0 ],
					"vs_wfg_shapes::shapewfg_freq_range" : [ 0.0 ],
					"vs_wfg_shapes::shapewfg_fm_range" : [ 0.0 ],
					"vs_wfg_shapes::shapewfg_dir" : [ 0.0 ],
					"vs_wfg_shapes::shapewfg_fm" : [ 0.094488188976378 ],
					"vs_wfg_shapes::shapewfg_freq" : [ 30.0 ],
					"vs_wfg_shapes::shapewfg_polygons" : [ 3.0 ],
					"vs_wfg_shapes::shapewfg_pw" : [ 27.165354330708663 ],
					"vs_wfg_shapes::shapewfg_pwm" : [ 0.0 ],
					"vs_wfg_shapes::shapewfg_shape" : [ 2.0 ],
					"vs_wfg_shapes::shapewfg_time" : [ 0.0 ],
					"vs_wfg_shapes::shapewfg_wf" : [ 4.0 ],
					"vs_wfg_shapes[1]::shapewfg_fm_range" : [ 0.0 ],
					"vs_wfg_shapes[1]::shapewfg_freq_range" : [ 0.0 ],
					"vs_wfg_shapes[1]::shapewfg_dir" : [ 0.0 ],
					"vs_wfg_shapes[1]::shapewfg_fm" : [ 0.0 ],
					"vs_wfg_shapes[1]::shapewfg_freq" : [ 30.0 ],
					"vs_wfg_shapes[1]::shapewfg_polygons" : [ 3.0 ],
					"vs_wfg_shapes[1]::shapewfg_pw" : [ 30.314960629921263 ],
					"vs_wfg_shapes[1]::shapewfg_pwm" : [ 0.0 ],
					"vs_wfg_shapes[1]::shapewfg_shape" : [ 2.0 ],
					"vs_wfg_shapes[1]::shapewfg_time" : [ 0.0 ],
					"vs_wfg_shapes[1]::shapewfg_wf" : [ 4.0 ],
					"vs_luma_key[1]::luma_invert" : [ 1.0 ],
					"vs_luma_key[1]::luma_smth" : [ 0.0 ],
					"vs_luma_key[1]::luma_thrshld" : [ 0.0 ],
					"vs_wfg_shapes[2]::shapewfg_freq_range" : [ 0.0 ],
					"vs_wfg_shapes[2]::shapewfg_fm_range" : [ 0.0 ],
					"vs_wfg_shapes[2]::shapewfg_dir" : [ 0.0 ],
					"vs_wfg_shapes[2]::shapewfg_fm" : [ 0.425196850393701 ],
					"vs_wfg_shapes[2]::shapewfg_freq" : [ 500.0 ],
					"vs_wfg_shapes[2]::shapewfg_polygons" : [ 3.0 ],
					"vs_wfg_shapes[2]::shapewfg_pw" : [ 50.0 ],
					"vs_wfg_shapes[2]::shapewfg_pwm" : [ 0.0 ],
					"vs_wfg_shapes[2]::shapewfg_shape" : [ 0.0 ],
					"vs_wfg_shapes[2]::shapewfg_time" : [ 6.0 ],
					"vs_wfg_shapes[2]::shapewfg_wf" : [ 0.0 ],
					"vs_luma_key[2]::luma_invert" : [ 0.0 ],
					"vs_luma_key[2]::luma_smth" : [ 0.0 ],
					"vs_luma_key[2]::luma_thrshld" : [ 0.54330762992126 ],
					"vs_luma_key[3]::luma_invert" : [ 0.0 ],
					"vs_luma_key[3]::luma_smth" : [ 0.0 ],
					"vs_luma_key[3]::luma_thrshld" : [ 0.0 ],
					"vs_blendmode_mixer::bm_ch1" : [ 1.0 ],
					"vs_blendmode_mixer::bm_ch2" : [ 1.0 ],
					"vs_blendmode_mixer::bm_master" : [ 1.0 ],
					"vs_blendmode_mixer::bm_mode" : [ 9.0 ],
					"vs_displacement[2]::displacement_gui::displacement_y_range" : [ 2.0 ],
					"vs_displacement[2]::displacement_gui::displacement_angle_range" : [ 2.0 ],
					"vs_displacement[2]::displacement_gui::displacement_scale_ym" : [ 2.0 ],
					"vs_displacement[2]::displacement_gui::displacement_scale_xm" : [ 2.0 ],
					"vs_displacement[2]::displacement_gui::displacement_x_range" : [ 2.0 ],
					"vs_displacement[2]::displacement_gui::displacement_anglemenu" : [ 3.0 ],
					"vs_displacement[2]::displacement_gui::displacement_angle" : [ 0.0 ],
					"vs_displacement[2]::displacement_gui::displacement_angle_m" : [ 0.0 ],
					"vs_displacement[2]::displacement_gui::displacement_x" : [ 0.0 ],
					"vs_displacement[2]::displacement_gui::displacement_x_m" : [ 0.0 ],
					"vs_displacement[2]::displacement_gui::displacement_y" : [ 0.0 ],
					"vs_displacement[2]::displacement_gui::displacement_y_m" : [ 0.0 ],
					"vs_displacement[2]::displacement_gui::displacement_zoom" : [ 1.015748031496063 ],
					"vs_displacement[2]::displacement_gui::displacement_zoom_m" : [ -0.006299212598425 ],
					"vs_displacement[2]::displacement_boundmode" : [ 0.0 ],
					"vs_displacement[2]::displacement_init_point" : [ 0.0 ],
					"vs_displacement[2]::displacement_polar" : [ 0.0 ]
				}

			}

		}

	}

}
