{
	"pattrstorage" : 	{
		"name" : "Vsynth",
		"slots" : 		{
			"1" : 			{
				"id" : 1,
				"data" : 				{
					"vs_colorizer::clrizer_color" : [ 0.92156862745098, 0.073562021652389, 0.0, 1.0, 0.013303769873304, 1.0, 0.46078431372549 ],
					"vs_colorizer::clrizer_hue" : [ 4.789357154389611 ],
					"vs_wfg_2[1]::wfg2_freq_range" : [ 0.0 ],
					"vs_wfg_2[1]::wfg2_fm_range" : [ 0.0 ],
					"vs_wfg_2[1]::wfg2_pm_range" : [ 0.0 ],
					"vs_wfg_2[1]::wfg2_fm" : [ 0.535433070866141 ],
					"vs_wfg_2[1]::wfg2_freq" : [ 0.0 ],
					"vs_wfg_2[1]::wfg2_pm" : [ 0.700787401574805 ],
					"vs_wfg_2[1]::wfg2_pw" : [ 27.16763825196854 ],
					"vs_wfg_2[1]::wfg2_pwm" : [ 0.0 ],
					"vs_wfg_2[1]::wfg2_sync_lock" : [ 2.0 ],
					"vs_wfg_2[1]::wfg2_time" : [ 2.0 ],
					"vs_wfg_2[1]::wfg2_time_range" : [ 0 ],
					"vs_wfg_2[1]::wfg2_wf" : [ 0.0 ],
					"bfgener8r::lozoom" : [ 1.0 ],
					"bfgener8r::speed" : [ 2.078740157480307 ],
					"bfgener8r::zoom-mult" : [ 1 ],
					"bfgener8r::hizoom" : [ -4.913385826771657 ],
					"vs_fish_eye::pixelador_dim" : [ 90.0 ],
					"vs_offset+rot::offrot_x_range" : [ 2.0 ],
					"vs_offset+rot::offrot_y_range" : [ 2.0 ],
					"vs_offset+rot::offrot_anglemenu" : [ 3.0 ],
					"vs_offset+rot::offrot_angle" : [ 0.0 ],
					"vs_offset+rot::offrot_boundmode" : [ 0.0 ],
					"vs_offset+rot::offrot_x" : [ 0.0 ],
					"vs_offset+rot::offrot_y" : [ 0.0 ],
					"vs_offset+rot::offrot_zoom" : [ 1.0 ],
					"vs_filter_temp::temp_freq" : [ 0.889763779527559 ],
					"vs_offset+rot[1]::offrot_y_range" : [ 2.0 ],
					"vs_offset+rot[1]::offrot_anglemenu" : [ 3.0 ],
					"vs_offset+rot[1]::offrot_x_range" : [ 2.0 ],
					"vs_offset+rot[1]::offrot_angle" : [ 0.0 ],
					"vs_offset+rot[1]::offrot_boundmode" : [ 0.0 ],
					"vs_offset+rot[1]::offrot_x" : [ 0.0 ],
					"vs_offset+rot[1]::offrot_y" : [ 0.0 ],
					"vs_offset+rot[1]::offrot_zoom" : [ 1.433070866141733 ],
					"vs_wfg_shapes::shapewfg_freq_range" : [ 0.0 ],
					"vs_wfg_shapes::shapewfg_fm_range" : [ 0.0 ],
					"vs_wfg_shapes::shapewfg_dir" : [ 0.0 ],
					"vs_wfg_shapes::shapewfg_fm" : [ 0.0 ],
					"vs_wfg_shapes::shapewfg_freq" : [ 41.527559055118104 ],
					"vs_wfg_shapes::shapewfg_polygons" : [ 3.0 ],
					"vs_wfg_shapes::shapewfg_pw" : [ 25.826771653543336 ],
					"vs_wfg_shapes::shapewfg_pwm" : [ 0.0 ],
					"vs_wfg_shapes::shapewfg_shape" : [ 2.0 ],
					"vs_wfg_shapes::shapewfg_time" : [ 0.0 ],
					"vs_wfg_shapes::shapewfg_wf" : [ 4.0 ],
					"vs_luma_key::luma_invert" : [ 0.0 ],
					"vs_luma_key::luma_smth" : [ 0.031496062992126 ],
					"vs_luma_key::luma_thrshld" : [ 0.464567393700786 ],
					"vs_luma_key[1]::luma_invert" : [ 1.0 ],
					"vs_luma_key[1]::luma_smth" : [ 0.102362204724409 ],
					"vs_luma_key[1]::luma_thrshld" : [ 0.716535149606299 ],
					"vs_luma_key[2]::luma_invert" : [ 0.0 ],
					"vs_luma_key[2]::luma_smth" : [ 0.023622047244094 ],
					"vs_luma_key[2]::luma_thrshld" : [ 0.45669337007874 ],
					"vs_offset+rot[2]::offrot_x_range" : [ 2.0 ],
					"vs_offset+rot[2]::offrot_y_range" : [ 2.0 ],
					"vs_offset+rot[2]::offrot_anglemenu" : [ 3.0 ],
					"vs_offset+rot[2]::offrot_angle" : [ 0.0 ],
					"vs_offset+rot[2]::offrot_boundmode" : [ 0.0 ],
					"vs_offset+rot[2]::offrot_x" : [ 0.0 ],
					"vs_offset+rot[2]::offrot_y" : [ 0.0 ],
					"vs_offset+rot[2]::offrot_zoom" : [ 1.0 ],
					"vs_colorizer[1]::clrizer_color" : [ 0.863701688134454, 0.352941176470588, 1.0, 1.0, 0.798226192398269, 1.0, 0.676470588235294 ],
					"vs_colorizer[1]::clrizer_hue" : [ 287.361429263376692 ],
					"vs_luma_key[3]::luma_invert" : [ 1.0 ],
					"vs_luma_key[3]::luma_smth" : [ 0.0 ],
					"vs_luma_key[3]::luma_thrshld" : [ 0.45669237007874 ],
					"vs_offset+rot[3]::offrot_x_range" : [ 2.0 ],
					"vs_offset+rot[3]::offrot_y_range" : [ 2.0 ],
					"vs_offset+rot[3]::offrot_anglemenu" : [ 3.0 ],
					"vs_offset+rot[3]::offrot_angle" : [ 45.0 ],
					"vs_offset+rot[3]::offrot_boundmode" : [ 3.0 ],
					"vs_offset+rot[3]::offrot_x" : [ 0.0 ],
					"vs_offset+rot[3]::offrot_y" : [ 0.0 ],
					"vs_offset+rot[3]::offrot_zoom" : [ 1.003937007874016 ],
					"vs_flip&swap::flip_x" : [ 1.0 ],
					"vs_flip&swap::flip_y" : [ 1.0 ],
					"vs_flip&swap::swap" : [ 1.0 ],
					"vs_offset+rot[4]::offrot_anglemenu" : [ 3.0 ],
					"vs_offset+rot[4]::offrot_y_range" : [ 2.0 ],
					"vs_offset+rot[4]::offrot_x_range" : [ 2.0 ],
					"vs_offset+rot[4]::offrot_angle" : [ 45.0 ],
					"vs_offset+rot[4]::offrot_boundmode" : [ 2.0 ],
					"vs_offset+rot[4]::offrot_x" : [ 0.0 ],
					"vs_offset+rot[4]::offrot_y" : [ 0.0 ],
					"vs_offset+rot[4]::offrot_zoom" : [ 1.468503937007874 ],
					"vs_offset+rot[5]::offrot_anglemenu" : [ 3.0 ],
					"vs_offset+rot[5]::offrot_y_range" : [ 2.0 ],
					"vs_offset+rot[5]::offrot_x_range" : [ 2.0 ],
					"vs_offset+rot[5]::offrot_angle" : [ -23.0 ],
					"vs_offset+rot[5]::offrot_boundmode" : [ 1.0 ],
					"vs_offset+rot[5]::offrot_x" : [ 0.0 ],
					"vs_offset+rot[5]::offrot_y" : [ 0.0 ],
					"vs_offset+rot[5]::offrot_zoom" : [ 1.0 ],
					"vs_convolve::kernel" : [ 11.0 ],
					"vs_convolve::r00" : [ -2.0 ],
					"vs_convolve::r01" : [ -1.0 ],
					"vs_convolve::r02" : [ 0.0 ],
					"vs_convolve::r10" : [ -1.0 ],
					"vs_convolve::r11" : [ 1.0 ],
					"vs_convolve::r12" : [ 1.0 ],
					"vs_convolve::r20" : [ 0.0 ],
					"vs_convolve::r21" : [ 1.0 ],
					"vs_convolve::r22" : [ 2.0 ],
					"vs_convolve::width" : [ 0.645669291338582 ],
					"vs_convolve[1]::kernel" : [ 4.0 ],
					"vs_convolve[1]::r00" : [ 0.0 ],
					"vs_convolve[1]::r01" : [ -1.0 ],
					"vs_convolve[1]::r02" : [ 0.0 ],
					"vs_convolve[1]::r10" : [ -1.0 ],
					"vs_convolve[1]::r11" : [ 4.0 ],
					"vs_convolve[1]::r12" : [ -1.0 ],
					"vs_convolve[1]::r20" : [ 0.0 ],
					"vs_convolve[1]::r21" : [ -1.0 ],
					"vs_convolve[1]::r22" : [ 0.0 ],
					"vs_convolve[1]::width" : [ 1.0 ],
					"vs_luma_key[4]::luma_invert" : [ 0.0 ],
					"vs_luma_key[4]::luma_smth" : [ 0.023622047244094 ],
					"vs_luma_key[4]::luma_thrshld" : [ 0.094488283464567 ],
					"vs_luma_key[5]::luma_invert" : [ 0.0 ],
					"vs_luma_key[5]::luma_smth" : [ 0.299212598425197 ],
					"vs_luma_key[5]::luma_thrshld" : [ 0.0 ],
					"vs_offset+rot[6]::offrot_x_range" : [ 2.0 ],
					"vs_offset+rot[6]::offrot_anglemenu" : [ 3.0 ],
					"vs_offset+rot[6]::offrot_y_range" : [ 2.0 ],
					"vs_offset+rot[6]::offrot_angle" : [ 180.0 ],
					"vs_offset+rot[6]::offrot_boundmode" : [ 0.0 ],
					"vs_offset+rot[6]::offrot_x" : [ 0.0 ],
					"vs_offset+rot[6]::offrot_y" : [ 0.0 ],
					"vs_offset+rot[6]::offrot_zoom" : [ 0.930944881889764 ],
					"vs_convolve[2]::kernel" : [ 3.0 ],
					"vs_convolve[2]::r00" : [ 1.0 ],
					"vs_convolve[2]::r01" : [ 0.0 ],
					"vs_convolve[2]::r02" : [ -1.0 ],
					"vs_convolve[2]::r10" : [ 0.0 ],
					"vs_convolve[2]::r11" : [ 0.0 ],
					"vs_convolve[2]::r12" : [ 0.0 ],
					"vs_convolve[2]::r20" : [ -1.0 ],
					"vs_convolve[2]::r21" : [ 0.0 ],
					"vs_convolve[2]::r22" : [ 1.0 ],
					"vs_convolve[2]::width" : [ 1.0 ],
					"vs_frame_delay::fd_fdbck" : [ 0.0 ],
					"vs_frame_delay::fd_mix" : [ 50.0 ],
					"vs_frame_delay::fd_time" : [ 30.0 ],
					"vs_frame_delay::fs_playback" : [ 0.0 ]
				}

			}

		}

	}

}
